textrank4ch/TextRank4Keyword.py
textrank4ch/TextRank4Sentence.py
textrank4ch/__init__.py
textrank4ch/segment.py
textrank4ch/test.py
textrank4ch/utils.py
textrank4ch-1.2.3.dist-info/LICENSE
textrank4ch-1.2.3.dist-info/METADATA
textrank4ch-1.2.3.dist-info/WHEEL
textrank4ch-1.2.3.dist-info/top_level.txt
textrank4ch-1.2.3.dist-info/RECORD
