Metadata-Version: 2.1
Name: textrank4ch
Version: 1.2.3
Summary: Key words extracting and Key sentences extracting
Home-page: https://github.com/skykiseki/textrank4ch
Author: Wei, Zhihui
Author-email: evelinesdd@qq.com
License: MIT
Keywords: NLP,Chinese,Chinese words,textrank
Platform: UNKNOWN
Classifier: Intended Audience :: Developers
Classifier: License :: OSI Approved :: MIT License
Classifier: Operating System :: OS Independent
Classifier: Natural Language :: Chinese (Simplified)
Classifier: Natural Language :: Chinese (Traditional)
Classifier: Programming Language :: Python
Classifier: Programming Language :: Python :: 3
Classifier: Programming Language :: Python :: 3.6
Classifier: Programming Language :: Python :: 3.7
Classifier: Topic :: Text Processing
Classifier: Topic :: Text Processing :: Indexing
Classifier: Topic :: Text Processing :: Linguistic
Requires-Python: >=3.6
License-File: LICENSE
Requires-Dist: pandas
Requires-Dist: numpy
Requires-Dist: jieba
Requires-Dist: networkx
